{
  "__query_params": {},
  "attachments": {},
  "case_id": "4babfd18417a",
  "closed": false,
  "date_closed": null,
  "date_modified": "2022-12-14T12:46:01.135000Z",
  "domain": "lwala-community-alliance",
  "indices": {},
  "properties": {
    "app_release": "Q2-2022",
    "case_type": "Household",
    "Last_Visit": "2022-12-02",
    "CHW_Name": "CAROLINE",
    "last_form_opened_date": "2022-12-02",
    "supervisor_visit": "none",
    "is_this_a_physical_home_visit_or_a_phone_call_visit": "physical_home_visit",
    "catchment": "Central Kamagambo",
    "date_opened": "2021-09-21T13:01:36.758",
    "sfid": "a030800",
    "did_you_complete_the_covid-19_phone_screening_for_this_household": "yes",
    "Treats_Drinking_Water": "Yes",
    "Active_Handwashing_Station": "Yes",
    "seed_input_support": "",
    "household_head_name": "d",
    "Drying_Rack": "Yes",
    "Kitchen_Garden": "Yes",
    "Clothesline": "Yes",
    "Name": "67851",
    "Female_Head_Name": "",
    "Check_Unborn_Child": "",
    "last_form_opened_date_and_time": "2022-12-02-11:39:38",
    "priority_household": "yes",
    "Functional_Latrine": "Yes",
    "test_user": "",
    "Area_Name": "Kanyingombe",
    "commcare_location_id": "1b7ff90563634b9daac6e44835e740b2",
    "Date": "2022-12-02",
    "CHW_ID": "a030800001zQrk5",
    "commcare_username": "caroline",
    "Rubbish_Pit": "Yes",
    "WASH_Compliant": "Yes",
    "owner_id": "40b2",
    "Core_WASH_Compliant": "Yes",
    "Total_Number_of_Members": "2",
    "case_name": "67851",
    "last_form_opened_name": "Update Household Revised",
    "external_id": null,
    "area": "a000800001OFYOz",
    "Improved_Cooking_Method": "Yes"
  },
  "server_date_modified": "2022-12-14T12:53:54.742231Z",
  "user_id": "43b77b80b464",
  "xform_ids": [
    "742ec663-c181-4e9f-9379-3a843ac6c2a7",
  ]
}
